Products.SQLAlchemyDA-2.2-py3.11-nspkg.pth
Products/SQLAlchemyDA/__init__.py
Products/SQLAlchemyDA/config.py
Products/SQLAlchemyDA/da.py
Products/SQLAlchemyDA/pt/addSAWrapperForm.zpt
Products/SQLAlchemyDA/pt/info.zpt
Products/SQLAlchemyDA/pt/query.zpt
Products/SQLAlchemyDA/tests/__init__.py
Products/SQLAlchemyDA/tests/test_SQLAlchemyDA.py
Products.SQLAlchemyDA-2.2.dist-info/LICENSE.txt
Products.SQLAlchemyDA-2.2.dist-info/METADATA
Products.SQLAlchemyDA-2.2.dist-info/WHEEL
Products.SQLAlchemyDA-2.2.dist-info/namespace_packages.txt
Products.SQLAlchemyDA-2.2.dist-info/top_level.txt
Products.SQLAlchemyDA-2.2.dist-info/RECORD
