Metadata-Version: 2.1
Name: Products.SQLAlchemyDA
Version: 2.2
Summary: A generic database adapter for Zope
Home-page: https://github.com/zopefoundation/Products.SQLAlchemyDA
Author: Andreas Jung
Author-email: info@zopyx.com
Maintainer: Zope Foundation and Contributors
Maintainer-email: zope-dev@zope.dev
License: ZPL 2.1
Project-URL: Issue Tracker, https://github.com/zopefoundation/Products.SQLAlchemyDA/issues
Project-URL: Sources, https://github.com/zopefoundation/Products.SQLAlchemyDA
Keywords: Zope Database adapter SQLAlchemy
Classifier: Development Status :: 5 - Production/Stable
Classifier: Intended Audience :: Developers
Classifier: License :: OSI Approved :: Zope Public License
Classifier: Operating System :: OS Independent
Classifier: Framework :: Zope
Classifier: Framework :: Zope :: 5
Classifier: Programming Language :: Python
Classifier: Topic :: Database
Classifier: Topic :: Database :: Front-Ends
Classifier: Topic :: Software Development :: Libraries :: Python Modules
Classifier: Programming Language :: Python :: 3.7
Classifier: Programming Language :: Python :: 3.8
Classifier: Programming Language :: Python :: 3.9
Classifier: Programming Language :: Python :: 3.10
Classifier: Programming Language :: Python :: 3.11
Classifier: Programming Language :: Python :: 3.12
Requires-Python: >=3.7
License-File: LICENSE.txt
Requires-Dist: setuptools
Requires-Dist: SQLAlchemy
Requires-Dist: z3c.sqlalchemy >1.5.1
Requires-Dist: Products.ZSQLMethods
Provides-Extra: test
Requires-Dist: testfixtures ; extra == 'test'
